{
  "nombre": "Super Pool",
  "nombre_original": "Super Pool",
  "sistema": "Acorn Archimedes",
  "year": "1991",
  "genres": [
    "Sports/Pool and Dart"
  ],
  "publisher": "4th Dimension",
  "aiDescription": "Super Pool para Acorn Archimedes, lanzado en 1991, representa un pináculo en las simulaciones de billar de su época. Los jugadores eran atraídos por su meticulosa recreación de la física del juego, permitiendo un control preciso sobre la potencia del tiro, el ángulo e incluso el efecto aplicado a la bola blanca. La interfaz intuitiva hacía accesible la complejidad del billar, desde el simple golpe hasta las carambolas más elaboradas, ofreciendo una experiencia inmersiva que desafiaba tanto a novatos como a veteranos del taco virtual.\nMás allá de su jugabilidad, Super Pool ocupa un lugar especial en la historia de los videojuegos como un ejemplo brillante de lo que el Acorn Archimedes era capaz de lograr. Sus gráficos detallados y su suave animación eran un testimonio del poder de la plataforma, estableciendo un estándar para futuros juegos de billar. Hoy, lo recordamos con cariño no solo como un entretenido simulador, sino como una pieza de museo que encapsula la innovación y el encanto de la era de los ordenadores domésticos de principios de los 90.",
  "aiHints": "¿Sabías que Super Pool fue aclamado por su motor de física increíblemente realista para la época? Esto permitía un nivel de precisión en los tiros que pocos juegos de billar habían logrado antes. - Un truco para los profesionales: dominar el 'efecto' (spin) en la bola blanca era clave. Aplicar el giro correcto no solo afectaba la trayectoria de la bola objetivo, sino que también era esencial para posicionar estratégicamente la bola blanca para el siguiente golpe, una habilidad que separaba a los maestros de los principiantes.",
  "tiene_review": false
}